factordb/__init__.py
factordb/cli.py
factordb/factordb.py
factordb_pycli-1.1.1.dist-info/DESCRIPTION.rst
factordb_pycli-1.1.1.dist-info/METADATA
factordb_pycli-1.1.1.dist-info/RECORD
factordb_pycli-1.1.1.dist-info/WHEEL
factordb_pycli-1.1.1.dist-info/entry_points.txt
factordb_pycli-1.1.1.dist-info/metadata.json
factordb_pycli-1.1.1.dist-info/top_level.txt
