Metadata-Version: 2.0
Name: factordb-pycli
Version: 1.1.1
Summary: The FactorDB CLI
Home-page: https://github.com/ryo-san470/factordb-pycli
Author: Ryosuke SATO (@ryo-san470)
Author-email: rskjtwp@gmail.com
License: MIT License
Platform: UNKNOWN
Classifier: Development Status :: 4 - Beta
Classifier: Environment :: Console
Classifier: Programming Language :: Python :: 2
Classifier: Programming Language :: Python :: 2.7
Classifier: Programming Language :: Python :: 3
Classifier: Programming Language :: Python :: 3.4
Classifier: Programming Language :: Python :: 3.5
Classifier: Programming Language :: Python :: 3.6
Classifier: Topic :: Utilities
Requires-Dist: requests
